Workbook

Sheet Tableau_de_Bord
A1: TABLEAU DE BORD FINANCIER CHRUTH
A2: Vue de decision : rentabilite mensuelle, point mort, tresorerie previsionnelle et priorisation des marches.
J3: Mois | K3: CA mensuel | L3: EBITDA | M3: Tresorerie cumulee
A4: CA mensuel | C4: Resultat mensuel | E4: Marge moyenne | G4: Point mort marches | J4: =Previsionnel_Global!A26 -> Janvier | K4: =Previsionnel_Global!D26 -> 2000 | L4: =Previsionnel_Global!F26 -> -2500 | M4: =Previsionnel_Global!L26 -> -22500
A5: =Synthese_Rentabilite!B5 -> 35382 | C5: =Synthese_Rentabilite!B9 -> -2255.64 | E5: =Synthese_Rentabilite!B11 -> 0.029855859 | G5: =Synthese_Rentabilite!B13 -> 25.082358 | J5: =Previsionnel_Global!A27 -> Fevrier | K5: =Previsionnel_Global!D27 -> 3960 | L5: =Previsionnel_Global!F27 -> -2010 | M5: =Previsionnel_Global!L27 -> -24510
J6: =Previsionnel_Global!A28 -> Mars | K6: =Previsionnel_Global!D28 -> 5880.8 | L6: =Previsionnel_Global!F28 -> -1529.8 | M6: =Previsionnel_Global!L28 -> -26039.8
A7: Tresorerie fin annee | C7: EBITDA annuel | E7: Marches actifs | G7: Taux marches rentables | J7: =Previsionnel_Global!A29 -> Avril | K7: =Previsionnel_Global!D29 -> 7763.184 | L7: =Previsionnel_Global!F29 -> -1059.204 | M7: =Previsionnel_Global!L29 -> -27099.004
A8: =Previsionnel_Global!O11 -> -20662.001 | C8: =Previsionnel_Global!O9 -> 277.98658 | E8: =Synthese_Rentabilite!B4 -> 8 | G8: =Synthese_Rentabilite!B17 -> 0.125 | J8: =Previsionnel_Global!A30 -> Mai | K8: =Previsionnel_Global!D30 -> 9607.9203 | L8: =Previsionnel_Global!F30 -> -598.01992 | M8: =Previsionnel_Global!L30 -> -27697.024
J9: =Previsionnel_Global!A31 -> Juin | K9: =Previsionnel_Global!D31 -> 11415.762 | L9: =Previsionnel_Global!F31 -> -146.05952 | M9: =Previsionnel_Global!L31 -> -27843.083
J10: =Previsionnel_Global!A32 -> Juillet | K10: =Previsionnel_Global!D32 -> 13187.447 | L10: =Previsionnel_Global!F32 -> 296.86167 | M10: =Previsionnel_Global!L32 -> -27546.222
A11: Lecture rapide | J11: =Previsionnel_Global!A33 -> Aout | K11: =Previsionnel_Global!D33 -> 14923.698 | L11: =Previsionnel_Global!F33 -> 730.92444 | M11: =Previsionnel_Global!L33 -> -26815.297
A12: =IF(Synthese_Rentabilite!B9<0,"Priorite: augmenter les prix ou baisser les heures/couts avant prospection massive.","Modele positif: concentrer la prospection sur les marches avec marge OK et CA recurrent.") -> Priorite: augmenter les prix ou baisser les heures/couts avant prospection massive. | J12: =Previsionnel_Global!A34 -> Septembre | K12: =Previsionnel_Global!D34 -> 16625.224 | L12: =Previsionnel_Global!F34 -> 1156.3059 | M12: =Previsionnel_Global!L34 -> -25739.735
J13: =Previsionnel_Global!A35 -> Octobre | K13: =Previsionnel_Global!D35 -> 18292.719 | L13: =Previsionnel_Global!F35 -> 1573.1798 | M13: =Previsionnel_Global!L35 -> -24351.516
J14: =Previsionnel_Global!A36 -> Novembre | K14: =Previsionnel_Global!D36 -> 19926.865 | L14: =Previsionnel_Global!F36 -> 1981.7162 | M14: =Previsionnel_Global!L36 -> -22656.896
J15: =Previsionnel_Global!A37 -> Decembre | K15: =Previsionnel_Global!D37 -> 21528.328 | L15: =Previsionnel_Global!F37 -> 2382.0819 | M15: =Previsionnel_Global!L37 -> -20662.001

Sheet Previsionnel_Global
A1: MODELE FINANCIER PREVISIONNEL CHRUTH
A2: Choisir un scenario et modifier les cellules jaunes. Les indicateurs, la tresorerie et le point mort se recalculent a l ouverture.
A4: Scenario selectionne | B4: Realiste | N4: --- BILAN DE L'EXERCICE ---
N5: Exercice (annee) | O5: =B22 -> 2026
A6: Scenario | B6: Conversion | C6: Panier annuel | D6: Couts var % | E6: Couts fixes/mois | N6: Point mort EBITDA (mois) | O6: =IFERROR(INDEX(A26:A37,MATCH(TRUE,INDEX(F26:F37>=0,0),0)),"non atteint") -> Juillet
A7: Pessimiste | B7: 0.02 | C7: 6000 | D7: 0.8 | E7: 3500 | N7: Delai de retour / payback (mois) | O7: =IFERROR(INDEX(A26:A37,MATCH(TRUE,INDEX(L26:L37>=0,0),0)),"non atteint") -> non atteint
A8: Realiste | B8: 0.03 | C8: 8000 | D8: 0.75 | E8: 3000 | N8: CA total exercice (EUR) | O8: =SUM(D26:D37) -> 145111.95
A9: Optimiste | B9: 0.05 | C9: 10000 | D9: 0.7 | E9: 2800 | N9: EBITDA total exercice (EUR) | O9: =SUM(F26:F37) -> 277.98658
N10: Resultat net total exercice (EUR) | O10: =SUM(J26:J37) -> -10662.001
A11: --- Hypotheses actives --- | N11: Tresorerie fin d'annee (EUR) | O11: =L37 -> -20662.001
A12: Prospects travailles / mois | B12: 100 | N12: VAN (EUR) | O12: =NPV((1+$B$19)^(1/12)-1,K26:K37) -> -20917.476
A13: Taux de conversion | B13: =INDEX(B7:B9,MATCH($B$4,A7:A9,0)) -> 0.03 | N13: TRI annuel | O13: =IFERROR((1+IRR(K26:K37))^12-1,"n/a") -> -0.83640785
A14: Panier moyen annuel / client (EUR) | B14: =INDEX(C7:C9,MATCH($B$4,A7:A9,0)) -> 8000 | N14: Clients actifs fin | O14: =C37 -> 32.292491
A15: Couts variables (% du CA) | B15: =INDEX(D7:D9,MATCH($B$4,A7:A9,0)) -> 0.75
A16: Couts fixes mensuels (EUR) | B16: =INDEX(E7:E9,MATCH($B$4,A7:A9,0)) -> 3000
A17: Churn mensuel | B17: 0.02
A18: CAPEX / investissement initial (EUR) | B18: 20000
A19: Taux d'actualisation annuel | B19: 0.1
A20: Taux d'imposition (IS) | B20: 0.25
A21: Amortissement CAPEX (mois) | B21: 24
A22: Annee de l'exercice | B22: 2026
A25: Mois | B25: Nouveaux clients | C25: Clients actifs | D25: CA mensuel (EUR) | E25: Marge brute (EUR) | F25: EBITDA (EUR) | G25: Amortissement (EUR) | H25: Resultat avant impot (EUR) | I25: Impot (EUR) | J25: Resultat net (EUR) | K25: Cash-flow (EUR) | L25: Tresorerie cumulee (EUR)
A26: Janvier | B26: =$B$12*$B$13 -> 3 | C26: =B26 -> 3 | D26: =C26*$B$14/12 -> 2000 | E26: =D26*(1-$B$15) -> 500 | F26: =E26-$B$16 -> -2500 | G26: =IF(1<=$B$21,$B$18/$B$21,0) -> 833.33333 | H26: =F26-G26 -> -3333.3333 | I26: =MAX(0,H26*$B$20) -> 0 | J26: =H26-I26 -> -3333.3333 | K26: =J26+G26-$B$18 -> -22500 | L26: =K26 -> -22500
A27: Fevrier | B27: =$B$12*$B$13 -> 3 | C27: =C26*(1-$B$17)+B27 -> 5.94 | D27: =C27*$B$14/12 -> 3960 | E27: =D27*(1-$B$15) -> 990 | F27: =E27-$B$16 -> -2010 | G27: =IF(2<=$B$21,$B$18/$B$21,0) -> 833.33333 | H27: =F27-G27 -> -2843.3333 | I27: =MAX(0,H27*$B$20) -> 0 | J27: =H27-I27 -> -2843.3333 | K27: =J27+G27 -> -2010 | L27: =L26+K27 -> -24510
A28: Mars | B28: =$B$12*$B$13 -> 3 | C28: =C27*(1-$B$17)+B28 -> 8.8212 | D28: =C28*$B$14/12 -> 5880.8 | E28: =D28*(1-$B$15) -> 1470.2 | F28: =E28-$B$16 -> -1529.8 | G28: =IF(3<=$B$21,$B$18/$B$21,0) -> 833.33333 | H28: =F28-G28 -> -2363.1333 | I28: =MAX(0,H28*$B$20) -> 0 | J28: =H28-I28 -> -2363.1333 | K28: =J28+G28 -> -1529.8 | L28: =L27+K28 -> -26039.8
A29: Avril | B29: =$B$12*$B$13 -> 3 | C29: =C28*(1-$B$17)+B29 -> 11.644776 | D29: =C29*$B$14/12 -> 7763.184 | E29: =D29*(1-$B$15) -> 1940.796 | F29: =E29-$B$16 -> -1059.204 | G29: =IF(4<=$B$21,$B$18/$B$21,0) -> 833.33333 | H29: =F29-G29 -> -1892.5373 | I29: =MAX(0,H29*$B$20) -> 0 | J29: =H29-I29 -> -1892.5373 | K29: =J29+G29 -> -1059.204 | L29: =L28+K29 -> -27099.004
A30: Mai | B30: =$B$12*$B$13 -> 3 | C30: =C29*(1-$B$17)+B30 -> 14.41188 | D30: =C30*$B$14/12 -> 9607.9203 | E30: =D30*(1-$B$15) -> 2401.9801 | F30: =E30-$B$16 -> -598.01992 | G30: =IF(5<=$B$21,$B$18/$B$21,0) -> 833.33333 | H30: =F30-G30 -> -1431.3533 | I30: =MAX(0,H30*$B$20) -> 0 | J30: =H30-I30 -> -1431.3533 | K30: =J30+G30 -> -598.01992 | L30: =L29+K30 -> -27697.024
A31: Juin | B31: =$B$12*$B$13 -> 3 | C31: =C30*(1-$B$17)+B31 -> 17.123643 | D31: =C31*$B$14/12 -> 11415.762 | E31: =D31*(1-$B$15) -> 2853.9405 | F31: =E31-$B$16 -> -146.05952 | G31: =IF(6<=$B$21,$B$18/$B$21,0) -> 833.33333 | H31: =F31-G31 -> -979.39285 | I31: =MAX(0,H31*$B$20) -> 0 | J31: =H31-I31 -> -979.39285 | K31: =J31+G31 -> -146.05952 | L31: =L30+K31 -> -27843.083
A32: Juillet | B32: =$B$12*$B$13 -> 3 | C32: =C31*(1-$B$17)+B32 -> 19.78117 | D32: =C32*$B$14/12 -> 13187.447 | E32: =D32*(1-$B$15) -> 3296.8617 | F32: =E32-$B$16 -> 296.86167 | G32: =IF(7<=$B$21,$B$18/$B$21,0) -> 833.33333 | H32: =F32-G32 -> -536.47166 | I32: =MAX(0,H32*$B$20) -> 0 | J32: =H32-I32 -> -536.47166 | K32: =J32+G32 -> 296.86167 | L32: =L31+K32 -> -27546.222
A33: Aout | B33: =$B$12*$B$13 -> 3 | C33: =C32*(1-$B$17)+B33 -> 22.385547 | D33: =C33*$B$14/12 -> 14923.698 | E33: =D33*(1-$B$15) -> 3730.9244 | F33: =E33-$B$16 -> 730.92444 | G33: =IF(8<=$B$21,$B$18/$B$21,0) -> 833.33333 | H33: =F33-G33 -> -102.4089 | I33: =MAX(0,H33*$B$20) -> 0 | J33: =H33-I33 -> -102.4089 | K33: =J33+G33 -> 730.92444 | L33: =L32+K33 -> -26815.297
A34: Septembre | B34: =$B$12*$B$13 -> 3 | C34: =C33*(1-$B$17)+B34 -> 24.937836 | D34: =C34*$B$14/12 -> 16625.224 | E34: =D34*(1-$B$15) -> 4156.3059 | F34: =E34-$B$16 -> 1156.3059 | G34: =IF(9<=$B$21,$B$18/$B$21,0) -> 833.33333 | H34: =F34-G34 -> 322.97261 | I34: =MAX(0,H34*$B$20) -> 80.743153 | J34: =H34-I34 -> 242.22946 | K34: =J34+G34 -> 1075.5628 | L34: =L33+K34 -> -25739.735
A35: Octobre | B35: =$B$12*$B$13 -> 3 | C35: =C34*(1-$B$17)+B35 -> 27.439079 | D35: =C35*$B$14/12 -> 18292.719 | E35: =D35*(1-$B$15) -> 4573.1798 | F35: =E35-$B$16 -> 1573.1798 | G35: =IF(10<=$B$21,$B$18/$B$21,0) -> 833.33333 | H35: =F35-G35 -> 739.84649 | I35: =MAX(0,H35*$B$20) -> 184.96162 | J35: =H35-I35 -> 554.88487 | K35: =J35+G35 -> 1388.2182 | L35: =L34+K35 -> -24351.516
A36: Novembre | B36: =$B$12*$B$13 -> 3 | C36: =C35*(1-$B$17)+B36 -> 29.890297 | D36: =C36*$B$14/12 -> 19926.865 | E36: =D36*(1-$B$15) -> 4981.7162 | F36: =E36-$B$16 -> 1981.7162 | G36: =IF(11<=$B$21,$B$18/$B$21,0) -> 833.33333 | H36: =F36-G36 -> 1148.3829 | I36: =MAX(0,H36*$B$20) -> 287.09572 | J36: =H36-I36 -> 861.28717 | K36: =J36+G36 -> 1694.6205 | L36: =L35+K36 -> -22656.896
A37: Decembre | B37: =$B$12*$B$13 -> 3 | C37: =C36*(1-$B$17)+B37 -> 32.292491 | D37: =C37*$B$14/12 -> 21528.328 | E37: =D37*(1-$B$15) -> 5382.0819 | F37: =E37-$B$16 -> 2382.0819 | G37: =IF(12<=$B$21,$B$18/$B$21,0) -> 833.33333 | H37: =F37-G37 -> 1548.7486 | I37: =MAX(0,H37*$B$20) -> 387.18714 | J37: =H37-I37 -> 1161.5614 | K37: =J37+G37 -> 1994.8948 | L37: =L36+K37 -> -20662.001

Sheet Marches
A1: RENTABILITE PAR MARCHE — saisir les cellules jaunes, le reste se calcule
A3: Nom du marche / client | B3: Jours/sem | C3: Heures/jour | D3: Effectif | E3: Type | F3: Produits par | G3: Cout produits/mois | H3: Prix du marche/mois | I3: Amortissement/mois | J3: Heures/mois | K3: Cout main d'oeuvre | L3: Cout produits | M3: Cout total | N3: Prix minimum cible | O3: Marge EUR | P3: Marge % | Q3: Statut marge | R3: Priorite business | S3: Ecart vs prix minimum | T3: Decision / action
A4: Bureaux Levallois | B4: 5 | C4: 3 | D4: 2 | E4: Jour | F4: Client | G4: 60 | H4: 1732 | I4: 50 | J4: =IF($A4="","",$B4*$C4*$D4*Hypotheses_Marche!$B$5) -> 129.9 | K4: =IF($A4="","",$J4*IF($E4="Nuit",Hypotheses_Marche!$B$4,Hypotheses_Marche!$B$3)) -> 2338.2 | L4: =IF($A4="","",IF(AND($F4="Nous",$H4<>""),IF($G4="",Hypotheses_Marche!$B$6,$G4),0)) -> 0 | M4: =IF($A4="","",$K4+$L4+$I4) -> 2388.2 | N4: =IF($A4="","",$M4/(1-Hypotheses_Marche!$B$7)) -> 2985.25 | O4: =IF($A4="","",$H4-$M4) -> -656.2 | P4: =IF(OR($A4="",$H4=0),"",$O4/$H4) -> -0.37886836 | Q4: =IF($A4="","",IF($P4>=Hypotheses_Marche!$B$7,"OK",IF($P4>=0,"A optimiser","Non rentable"))) -> Non rentable | R4: =IF($A4="","",IF(AND($P4>=Hypotheses_Marche!$B$7,$O4>=1000),"Prioritaire",IF($P4<0,"A refuser/renegocier","A surveiller"))) -> A refuser/renegocier | S4: =IF($A4="","",$H4-$N4) -> -1253.25 | T4: =IF($A4="","",IF($P4<0,"Renegocier prix/couts",IF($P4<Hypotheses_Marche!$B$7,"Optimiser heures/produits","Conserver"))) -> Renegocier prix/couts
A5: Clinique Paris 12 (nuit) | B5: 6 | C5: 4 | D5: 3 | E5: Nuit | F5: Client | G5: 0 | H5: 8500 | I5: 120 | J5: =IF($A5="","",$B5*$C5*$D5*Hypotheses_Marche!$B$5) -> 311.76 | K5: =IF($A5="","",$J5*IF($E5="Nuit",Hypotheses_Marche!$B$4,Hypotheses_Marche!$B$3)) -> 7170.48 | L5: =IF($A5="","",IF(AND($F5="Nous",$H5<>""),IF($G5="",Hypotheses_Marche!$B$6,$G5),0)) -> 0 | M5: =IF($A5="","",$K5+$L5+$I5) -> 7290.48 | N5: =IF($A5="","",$M5/(1-Hypotheses_Marche!$B$7)) -> 9113.1 | O5: =IF($A5="","",$H5-$M5) -> 1209.52 | P5: =IF(OR($A5="",$H5=0),"",$O5/$H5) -> 0.14229647 | Q5: =IF($A5="","",IF($P5>=Hypotheses_Marche!$B$7,"OK",IF($P5>=0,"A optimiser","Non rentable"))) -> A optimiser | R5: =IF($A5="","",IF(AND($P5>=Hypotheses_Marche!$B$7,$O5>=1000),"Prioritaire",IF($P5<0,"A refuser/renegocier","A surveiller"))) -> A surveiller | S5: =IF($A5="","",$H5-$N5) -> -613.1 | T5: =IF($A5="","",IF($P5<0,"Renegocier prix/couts",IF($P5<Hypotheses_Marche!$B$7,"Optimiser heures/produits","Conserver"))) -> Optimiser heures/produits
A6: Ecole primaire Montreuil | B6: 4 | C6: 2 | D6: 2 | E6: Jour | F6: Nous | G6: 80 | H6: 1600 | I6: 40 | J6: =IF($A6="","",$B6*$C6*$D6*Hypotheses_Marche!$B$5) -> 69.28 | K6: =IF($A6="","",$J6*IF($E6="Nuit",Hypotheses_Marche!$B$4,Hypotheses_Marche!$B$3)) -> 1247.04 | L6: =IF($A6="","",IF(AND($F6="Nous",$H6<>""),IF($G6="",Hypotheses_Marche!$B$6,$G6),0)) -> 80 | M6: =IF($A6="","",$K6+$L6+$I6) -> 1367.04 | N6: =IF($A6="","",$M6/(1-Hypotheses_Marche!$B$7)) -> 1708.8 | O6: =IF($A6="","",$H6-$M6) -> 232.96 | P6: =IF(OR($A6="",$H6=0),"",$O6/$H6) -> 0.1456 | Q6: =IF($A6="","",IF($P6>=Hypotheses_Marche!$B$7,"OK",IF($P6>=0,"A optimiser","Non rentable"))) -> A optimiser | R6: =IF($A6="","",IF(AND($P6>=Hypotheses_Marche!$B$7,$O6>=1000),"Prioritaire",IF($P6<0,"A refuser/renegocier","A surveiller"))) -> A surveiller | S6: =IF($A6="","",$H6-$N6) -> -108.8 | T6: =IF($A6="","",IF($P6<0,"Renegocier prix/couts",IF($P6<Hypotheses_Marche!$B$7,"Optimiser heures/produits","Conserver"))) -> Optimiser heures/produits
A7: Centre commercial Bobigny | B7: 7 | C7: 5 | D7: 4 | E7: Nuit | F7: Nous | G7: 200 | H7: 13000 | I7: 150 | J7: =IF($A7="","",$B7*$C7*$D7*Hypotheses_Marche!$B$5) -> 606.2 | K7: =IF($A7="","",$J7*IF($E7="Nuit",Hypotheses_Marche!$B$4,Hypotheses_Marche!$B$3)) -> 13942.6 | L7: =IF($A7="","",IF(AND($F7="Nous",$H7<>""),IF($G7="",Hypotheses_Marche!$B$6,$G7),0)) -> 200 | M7: =IF($A7="","",$K7+$L7+$I7) -> 14292.6 | N7: =IF($A7="","",$M7/(1-Hypotheses_Marche!$B$7)) -> 17865.75 | O7: =IF($A7="","",$H7-$M7) -> -1292.6 | P7: =IF(OR($A7="",$H7=0),"",$O7/$H7) -> -0.099430769 | Q7: =IF($A7="","",IF($P7>=Hypotheses_Marche!$B$7,"OK",IF($P7>=0,"A optimiser","Non rentable"))) -> Non rentable | R7: =IF($A7="","",IF(AND($P7>=Hypotheses_Marche!$B$7,$O7>=1000),"Prioritaire",IF($P7<0,"A refuser/renegocier","A surveiller"))) -> A refuser/renegocier | S7: =IF($A7="","",$H7-$N7) -> -4865.75 | T7: =IF($A7="","",IF($P7<0,"Renegocier prix/couts",IF($P7<Hypotheses_Marche!$B$7,"Optimiser heures/produits","Conserver"))) -> Renegocier prix/couts
A8: Cabinet medical Neuilly | B8: 3 | C8: 2 | D8: 1 | E8: Jour | F8: Client | G8: 0 | H8: 650 | I8: 20 | J8: =IF($A8="","",$B8*$C8*$D8*Hypotheses_Marche!$B$5) -> 25.98 | K8: =IF($A8="","",$J8*IF($E8="Nuit",Hypotheses_Marche!$B$4,Hypotheses_Marche!$B$3)) -> 467.64 | L8: =IF($A8="","",IF(AND($F8="Nous",$H8<>""),IF($G8="",Hypotheses_Marche!$B$6,$G8),0)) -> 0 | M8: =IF($A8="","",$K8+$L8+$I8) -> 487.64 | N8: =IF($A8="","",$M8/(1-Hypotheses_Marche!$B$7)) -> 609.55 | O8: =IF($A8="","",$H8-$M8) -> 162.36 | P8: =IF(OR($A8="",$H8=0),"",$O8/$H8) -> 0.24978462 | Q8: =IF($A8="","",IF($P8>=Hypotheses_Marche!$B$7,"OK",IF($P8>=0,"A optimiser","Non rentable"))) -> OK | R8: =IF($A8="","",IF(AND($P8>=Hypotheses_Marche!$B$7,$O8>=1000),"Prioritaire",IF($P8<0,"A refuser/renegocier","A surveiller"))) -> A surveiller | S8: =IF($A8="","",$H8-$N8) -> 40.45 | T8: =IF($A8="","",IF($P8<0,"Renegocier prix/couts",IF($P8<Hypotheses_Marche!$B$7,"Optimiser heures/produits","Conserver"))) -> Conserver
A9: Mairie annexe Pantin | B9: 5 | C9: 3 | D9: 2 | E9: Jour | F9: Nous | G9: 70 | H9: 2900 | I9: 60 | J9: =IF($A9="","",$B9*$C9*$D9*Hypotheses_Marche!$B$5) -> 129.9 | K9: =IF($A9="","",$J9*IF($E9="Nuit",Hypotheses_Marche!$B$4,Hypotheses_Marche!$B$3)) -> 2338.2 | L9: =IF($A9="","",IF(AND($F9="Nous",$H9<>""),IF($G9="",Hypotheses_Marche!$B$6,$G9),0)) -> 70 | M9: =IF($A9="","",$K9+$L9+$I9) -> 2468.2 | N9: =IF($A9="","",$M9/(1-Hypotheses_Marche!$B$7)) -> 3085.25 | O9: =IF($A9="","",$H9-$M9) -> 431.8 | P9: =IF(OR($A9="",$H9=0),"",$O9/$H9) -> 0.14889655 | Q9: =IF($A9="","",IF($P9>=Hypotheses_Marche!$B$7,"OK",IF($P9>=0,"A optimiser","Non rentable"))) -> A optimiser | R9: =IF($A9="","",IF(AND($P9>=Hypotheses_Marche!$B$7,$O9>=1000),"Prioritaire",IF($P9<0,"A refuser/renegocier","A surveiller"))) -> A surveiller | S9: =IF($A9="","",$H9-$N9) -> -185.25 | T9: =IF($A9="","",IF($P9<0,"Renegocier prix/couts",IF($P9<Hypotheses_Marche!$B$7,"Optimiser heures/produits","Conserver"))) -> Optimiser heures/produits
A10: Restaurant Bastille | B10: 6 | C10: 2 | D10: 1 | E10: Nuit | F10: Nous | G10: 50 | H10: 1500 | I10: 30 | J10: =IF($A10="","",$B10*$C10*$D10*Hypotheses_Marche!$B$5) -> 51.96 | K10: =IF($A10="","",$J10*IF($E10="Nuit",Hypotheses_Marche!$B$4,Hypotheses_Marche!$B$3)) -> 1195.08 | L10: =IF($A10="","",IF(AND($F10="Nous",$H10<>""),IF($G10="",Hypotheses_Marche!$B$6,$G10),0)) -> 50 | M10: =IF($A10="","",$K10+$L10+$I10) -> 1275.08 | N10: =IF($A10="","",$M10/(1-Hypotheses_Marche!$B$7)) -> 1593.85 | O10: =IF($A10="","",$H10-$M10) -> 224.92 | P10: =IF(OR($A10="",$H10=0),"",$O10/$H10) -> 0.14994667 | Q10: =IF($A10="","",IF($P10>=Hypotheses_Marche!$B$7,"OK",IF($P10>=0,"A optimiser","Non rentable"))) -> A optimiser | R10: =IF($A10="","",IF(AND($P10>=Hypotheses_Marche!$B$7,$O10>=1000),"Prioritaire",IF($P10<0,"A refuser/renegocier","A surveiller"))) -> A surveiller | S10: =IF($A10="","",$H10-$N10) -> -93.85 | T10: =IF($A10="","",IF($P10<0,"Renegocier prix/couts",IF($P10<Hypotheses_Marche!$B$7,"Optimiser heures/produits","Conserver"))) -> Optimiser heures/produits
A11: Coworking Republique | B11: 5 | C11: 4 | D11: 3 | E11: Jour | F11: Client | G11: 0 | H11: 5500 | I11: 80 | J11: =IF($A11="","",$B11*$C11*$D11*Hypotheses_Marche!$B$5) -> 259.8 | K11: =IF($A11="","",$J11*IF($E11="Nuit",Hypotheses_Marche!$B$4,Hypotheses_Marche!$B$3)) -> 4676.4 | L11: =IF($A11="","",IF(AND($F11="Nous",$H11<>""),IF($G11="",Hypotheses_Marche!$B$6,$G11),0)) -> 0 | M11: =IF($A11="","",$K11+$L11+$I11) -> 4756.4 | N11: =IF($A11="","",$M11/(1-Hypotheses_Marche!$B$7)) -> 5945.5 | O11: =IF($A11="","",$H11-$M11) -> 743.6 | P11: =IF(OR($A11="",$H11=0),"",$O11/$H11) -> 0.1352 | Q11: =IF($A11="","",IF($P11>=Hypotheses_Marche!$B$7,"OK",IF($P11>=0,"A optimiser","Non rentable"))) -> A optimiser | R11: =IF($A11="","",IF(AND($P11>=Hypotheses_Marche!$B$7,$O11>=1000),"Prioritaire",IF($P11<0,"A refuser/renegocier","A surveiller"))) -> A surveiller | S11: =IF($A11="","",$H11-$N11) -> -445.5 | T11: =IF($A11="","",IF($P11<0,"Renegocier prix/couts",IF($P11<Hypotheses_Marche!$B$7,"Optimiser heures/produits","Conserver"))) -> Optimiser heures/produits
E12: Jour | F12: Nous | J12: =IF($A12="","",$B12*$C12*$D12*Hypotheses_Marche!$B$5) | K12: =IF($A12="","",$J12*IF($E12="Nuit",Hypotheses_Marche!$B$4,Hypotheses_Marche!$B$3)) | L12: =IF($A12="","",IF(AND($F12="Nous",$H12<>""),IF($G12="",Hypotheses_Marche!$B$6,$G12),0)) | M12: =IF($A12="","",$K12+$L12+$I12) | N12: =IF($A12="","",$M12/(1-Hypotheses_Marche!$B$7)) | O12: =IF($A12="","",$H12-$M12) | P12: =IF(OR($A12="",$H12=0),"",$O12/$H12) | Q12: =IF($A12="","",IF($P12>=Hypotheses_Marche!$B$7,"OK",IF($P12>=0,"A optimiser","Non rentable"))) | R12: =IF($A12="","",IF(AND($P12>=Hypotheses_Marche!$B$7,$O12>=1000),"Prioritaire",IF($P12<0,"A refuser/renegocier","A surveiller"))) | S12: =IF($A12="","",$H12-$N12) | T12: =IF($A12="","",IF($P12<0,"Renegocier prix/couts",IF($P12<Hypotheses_Marche!$B$7,"Optimiser heures/produits","Conserver")))
E13: Jour | F13: Nous | J13: =IF($A13="","",$B13*$C13*$D13*Hypotheses_Marche!$B$5) | K13: =IF($A13="","",$J13*IF($E13="Nuit",Hypotheses_Marche!$B$4,Hypotheses_Marche!$B$3)) | L13: =IF($A13="","",IF(AND($F13="Nous",$H13<>""),IF($G13="",Hypotheses_Marche!$B$6,$G13),0)) | M13: =IF($A13="","",$K13+$L13+$I13) | N13: =IF($A13="","",$M13/(1-Hypotheses_Marche!$B$7)) | O13: =IF($A13="","",$H13-$M13) | P13: =IF(OR($A13="",$H13=0),"",$O13/$H13) | Q13: =IF($A13="","",IF($P13>=Hypotheses_Marche!$B$7,"OK",IF($P13>=0,"A optimiser","Non rentable"))) | R13: =IF($A13="","",IF(AND($P13>=Hypotheses_Marche!$B$7,$O13>=1000),"Prioritaire",IF($P13<0,"A refuser/renegocier","A surveiller"))) | S13: =IF($A13="","",$H13-$N13) | T13: =IF($A13="","",IF($P13<0,"Renegocier prix/couts",IF($P13<Hypotheses_Marche!$B$7,"Optimiser heures/produits","Conserver")))
E14: Jour | F14: Nous | J14: =IF($A14="","",$B14*$C14*$D14*Hypotheses_Marche!$B$5) | K14: =IF($A14="","",$J14*IF($E14="Nuit",Hypotheses_Marche!$B$4,Hypotheses_Marche!$B$3)) | L14: =IF($A14="","",IF(AND($F14="Nous",$H14<>""),IF($G14="",Hypotheses_Marche!$B$6,$G14),0)) | M14: =IF($A14="","",$K14+$L14+$I14) | N14: =IF($A14="","",$M14/(1-Hypotheses_Marche!$B$7)) | O14: =IF($A14="","",$H14-$M14) | P14: =IF(OR($A14="",$H14=0),"",$O14/$H14) | Q14: =IF($A14="","",IF($P14>=Hypotheses_Marche!$B$7,"OK",IF($P14>=0,"A optimiser","Non rentable"))) | R14: =IF($A14="","",IF(AND($P14>=Hypotheses_Marche!$B$7,$O14>=1000),"Prioritaire",IF($P14<0,"A refuser/renegocier","A surveiller"))) | S14: =IF($A14="","",$H14-$N14) | T14: =IF($A14="","",IF($P14<0,"Renegocier prix/couts",IF($P14<Hypotheses_Marche!$B$7,"Optimiser heures/produits","Conserver")))
E15: Jour | F15: Nous | J15: =IF($A15="","",$B15*$C15*$D15*Hypotheses_Marche!$B$5) | K15: =IF($A15="","",$J15*IF($E15="Nuit",Hypotheses_Marche!$B$4,Hypotheses_Marche!$B$3)) | L15: =IF($A15="","",IF(AND($F15="Nous",$H15<>""),IF($G15="",Hypotheses_Marche!$B$6,$G15),0)) | M15: =IF($A15="","",$K15+$L15+$I15) | N15: =IF($A15="","",$M15/(1-Hypotheses_Marche!$B$7)) | O15: =IF($A15="","",$H15-$M15) | P15: =IF(OR($A15="",$H15=0),"",$O15/$H15) | Q15: =IF($A15="","",IF($P15>=Hypotheses_Marche!$B$7,"OK",IF($P15>=0,"A optimiser","Non rentable"))) | R15: =IF($A15="","",IF(AND($P15>=Hypotheses_Marche!$B$7,$O15>=1000),"Prioritaire",IF($P15<0,"A refuser/renegocier","A surveiller"))) | S15: =IF($A15="","",$H15-$N15) | T15: =IF($A15="","",IF($P15<0,"Renegocier prix/couts",IF($P15<Hypotheses_Marche!$B$7,"Optimiser heures/produits","Conserver")))
E16: Jour | F16: Nous | J16: =IF($A16="","",$B16*$C16*$D16*Hypotheses_Marche!$B$5) | K16: =IF($A16="","",$J16*IF($E16="Nuit",Hypotheses_Marche!$B$4,Hypotheses_Marche!$B$3)) | L16: =IF($A16="","",IF(AND($F16="Nous",$H16<>""),IF($G16="",Hypotheses_Marche!$B$6,$G16),0)) | M16: =IF($A16="","",$K16+$L16+$I16) | N16: =IF($A16="","",$M16/(1-Hypotheses_Marche!$B$7)) | O16: =IF($A16="","",$H16-$M16) | P16: =IF(OR($A16="",$H16=0),"",$O16/$H16) | Q16: =IF($A16="","",IF($P16>=Hypotheses_Marche!$B$7,"OK",IF($P16>=0,"A optimiser","Non rentable"))) | R16: =IF($A16="","",IF(AND($P16>=Hypotheses_Marche!$B$7,$O16>=1000),"Prioritaire",IF($P16<0,"A refuser/renegocier","A surveiller"))) | S16: =IF($A16="","",$H16-$N16) | T16: =IF($A16="","",IF($P16<0,"Renegocier prix/couts",IF($P16<Hypotheses_Marche!$B$7,"Optimiser heures/produits","Conserver")))
E17: Jour | F17: Nous | J17: =IF($A17="","",$B17*$C17*$D17*Hypotheses_Marche!$B$5) | K17: =IF($A17="","",$J17*IF($E17="Nuit",Hypotheses_Marche!$B$4,Hypotheses_Marche!$B$3)) | L17: =IF($A17="","",IF(AND($F17="Nous",$H17<>""),IF($G17="",Hypotheses_Marche!$B$6,$G17),0)) | M17: =IF($A17="","",$K17+$L17+$I17) | N17: =IF($A17="","",$M17/(1-Hypotheses_Marche!$B$7)) | O17: =IF($A17="","",$H17-$M17) | P17: =IF(OR($A17="",$H17=0),"",$O17/$H17) | Q17: =IF($A17="","",IF($P17>=Hypotheses_Marche!$B$7,"OK",IF($P17>=0,"A optimiser","Non rentable"))) | R17: =IF($A17="","",IF(AND($P17>=Hypotheses_Marche!$B$7,$O17>=1000),"Prioritaire",IF($P17<0,"A refuser/renegocier","A surveiller"))) | S17: =IF($A17="","",$H17-$N17) | T17: =IF($A17="","",IF($P17<0,"Renegocier prix/couts",IF($P17<Hypotheses_Marche!$B$7,"Optimiser heures/produits","Conserver")))
E18: Jour | F18: Nous | J18: =IF($A18="","",$B18*$C18*$D18*Hypotheses_Marche!$B$5) | K18: =IF($A18="","",$J18*IF($E18="Nuit",Hypotheses_Marche!$B$4,Hypotheses_Marche!$B$3)) | L18: =IF($A18="","",IF(AND($F18="Nous",$H18<>""),IF($G18="",Hypotheses_Marche!$B$6,$G18),0)) | M18: =IF($A18="","",$K18+$L18+$I18) | N18: =IF($A18="","",$M18/(1-Hypotheses_Marche!$B$7)) | O18: =IF($A18="","",$H18-$M18) | P18: =IF(OR($A18="",$H18=0),"",$O18/$H18) | Q18: =IF($A18="","",IF($P18>=Hypotheses_Marche!$B$7,"OK",IF($P18>=0,"A optimiser","Non rentable"))) | R18: =IF($A18="","",IF(AND($P18>=Hypotheses_Marche!$B$7,$O18>=1000),"Prioritaire",IF($P18<0,"A refuser/renegocier","A surveiller"))) | S18: =IF($A18="","",$H18-$N18) | T18: =IF($A18="","",IF($P18<0,"Renegocier prix/couts",IF($P18<Hypotheses_Marche!$B$7,"Optimiser heures/produits","Conserver")))
E19: Jour | F19: Nous | J19: =IF($A19="","",$B19*$C19*$D19*Hypotheses_Marche!$B$5) | K19: =IF($A19="","",$J19*IF($E19="Nuit",Hypotheses_Marche!$B$4,Hypotheses_Marche!$B$3)) | L19: =IF($A19="","",IF(AND($F19="Nous",$H19<>""),IF($G19="",Hypotheses_Marche!$B$6,$G19),0)) | M19: =IF($A19="","",$K19+$L19+$I19) | N19: =IF($A19="","",$M19/(1-Hypotheses_Marche!$B$7)) | O19: =IF($A19="","",$H19-$M19) | P19: =IF(OR($A19="",$H19=0),"",$O19/$H19) | Q19: =IF($A19="","",IF($P19>=Hypotheses_Marche!$B$7,"OK",IF($P19>=0,"A optimiser","Non rentable"))) | R19: =IF($A19="","",IF(AND($P19>=Hypotheses_Marche!$B$7,$O19>=1000),"Prioritaire",IF($P19<0,"A refuser/renegocier","A surveiller"))) | S19: =IF($A19="","",$H19-$N19) | T19: =IF($A19="","",IF($P19<0,"Renegocier prix/couts",IF($P19<Hypotheses_Marche!$B$7,"Optimiser heures/produits","Conserver")))
E20: Jour | F20: Nous | J20: =IF($A20="","",$B20*$C20*$D20*Hypotheses_Marche!$B$5) | K20: =IF($A20="","",$J20*IF($E20="Nuit",Hypotheses_Marche!$B$4,Hypotheses_Marche!$B$3)) | L20: =IF($A20="","",IF(AND($F20="Nous",$H20<>""),IF($G20="",Hypotheses_Marche!$B$6,$G20),0)) | M20: =IF($A20="","",$K20+$L20+$I20) | N20: =IF($A20="","",$M20/(1-Hypotheses_Marche!$B$7)) | O20: =IF($A20="","",$H20-$M20) | P20: =IF(OR($A20="",$H20=0),"",$O20/$H20) | Q20: =IF($A20="","",IF($P20>=Hypotheses_Marche!$B$7,"OK",IF($P20>=0,"A optimiser","Non rentable"))) | R20: =IF($A20="","",IF(AND($P20>=Hypotheses_Marche!$B$7,$O20>=1000),"Prioritaire",IF($P20<0,"A refuser/renegocier","A surveiller"))) | S20: =IF($A20="","",$H20-$N20) | T20: =IF($A20="","",IF($P20<0,"Renegocier prix/couts",IF($P20<Hypotheses_Marche!$B$7,"Optimiser heures/produits","Conserver")))
E21: Jour | F21: Nous | J21: =IF($A21="","",$B21*$C21*$D21*Hypotheses_Marche!$B$5) | K21: =IF($A21="","",$J21*IF($E21="Nuit",Hypotheses_Marche!$B$4,Hypotheses_Marche!$B$3)) | L21: =IF($A21="","",IF(AND($F21="Nous",$H21<>""),IF($G21="",Hypotheses_Marche!$B$6,$G21),0)) | M21: =IF($A21="","",$K21+$L21+$I21) | N21: =IF($A21="","",$M21/(1-Hypotheses_Marche!$B$7)) | O21: =IF($A21="","",$H21-$M21) | P21: =IF(OR($A21="",$H21=0),"",$O21/$H21) | Q21: =IF($A21="","",IF($P21>=Hypotheses_Marche!$B$7,"OK",IF($P21>=0,"A optimiser","Non rentable"))) | R21: =IF($A21="","",IF(AND($P21>=Hypotheses_Marche!$B$7,$O21>=1000),"Prioritaire",IF($P21<0,"A refuser/renegocier","A surveiller"))) | S21: =IF($A21="","",$H21-$N21) | T21: =IF($A21="","",IF($P21<0,"Renegocier prix/couts",IF($P21<Hypotheses_Marche!$B$7,"Optimiser heures/produits","Conserver")))
E22: Jour | F22: Nous | J22: =IF($A22="","",$B22*$C22*$D22*Hypotheses_Marche!$B$5) | K22: =IF($A22="","",$J22*IF($E22="Nuit",Hypotheses_Marche!$B$4,Hypotheses_Marche!$B$3)) | L22: =IF($A22="","",IF(AND($F22="Nous",$H22<>""),IF($G22="",Hypotheses_Marche!$B$6,$G22),0)) | M22: =IF($A22="","",$K22+$L22+$I22) | N22: =IF($A22="","",$M22/(1-Hypotheses_Marche!$B$7)) | O22: =IF($A22="","",$H22-$M22) | P22: =IF(OR($A22="",$H22=0),"",$O22/$H22) | Q22: =IF($A22="","",IF($P22>=Hypotheses_Marche!$B$7,"OK",IF($P22>=0,"A optimiser","Non rentable"))) | R22: =IF($A22="","",IF(AND($P22>=Hypotheses_Marche!$B$7,$O22>=1000),"Prioritaire",IF($P22<0,"A refuser/renegocier","A surveiller"))) | S22: =IF($A22="","",$H22-$N22) | T22: =IF($A22="","",IF($P22<0,"Renegocier prix/couts",IF($P22<Hypotheses_Marche!$B$7,"Optimiser heures/produits","Conserver")))
E23: Jour | F23: Nous | J23: =IF($A23="","",$B23*$C23*$D23*Hypotheses_Marche!$B$5) | K23: =IF($A23="","",$J23*IF($E23="Nuit",Hypotheses_Marche!$B$4,Hypotheses_Marche!$B$3)) | L23: =IF($A23="","",IF(AND($F23="Nous",$H23<>""),IF($G23="",Hypotheses_Marche!$B$6,$G23),0)) | M23: =IF($A23="","",$K23+$L23+$I23) | N23: =IF($A23="","",$M23/(1-Hypotheses_Marche!$B$7)) | O23: =IF($A23="","",$H23-$M23) | P23: =IF(OR($A23="",$H23=0),"",$O23/$H23) | Q23: =IF($A23="","",IF($P23>=Hypotheses_Marche!$B$7,"OK",IF($P23>=0,"A optimiser","Non rentable"))) | R23: =IF($A23="","",IF(AND($P23>=Hypotheses_Marche!$B$7,$O23>=1000),"Prioritaire",IF($P23<0,"A refuser/renegocier","A surveiller"))) | S23: =IF($A23="","",$H23-$N23) | T23: =IF($A23="","",IF($P23<0,"Renegocier prix/couts",IF($P23<Hypotheses_Marche!$B$7,"Optimiser heures/produits","Conserver")))
... E25: Jour | F25: Nous | J25: =IF($A25="","",$B25*$C25*$D25*Hypotheses_Marche!$B$5) | K25: =IF($A25="","",$J25*IF($E25="Nuit",Hypotheses_Marche!$B$4,Hypotheses_Marche!$B$3)) | L25: =IF($A25="","",IF(AND($F25="Nous",$H25<>""),IF($G25="",Hypotheses_Marche!$B$6,$G25),0)) | M25: =IF($A25="","",$K25+$L25+$I25) | N25: =IF($A25="","",$M25/(1-Hypotheses_Marche!$B$7)) | O25: =IF($A25="","",$H25-$M25) | P25: =IF(OR($A25="",$H25=0),"",$O25/$H25) | Q25: =IF($A25="","",IF($P25>=Hypotheses_Marche!$B$7,"OK",IF($P25>=0,"A optimiser","Non rentable"))) | R25: =IF($A25="","",IF(AND($P25>=Hypotheses_Marche!$B$7,$O25>=1000),"Prioritaire",IF($P25<0,"A refuser/renegocier","A surveiller"))) | S25: =IF($A25="","",$H25-$N25) | T25: =IF($A25="","",IF($P25<0,"Renegocier prix/couts",IF($P25<Hypotheses_Marche!$B$7,"Optimiser heures/produits","Conserver")))

Sheet Synthese_Rentabilite
A1: SYNTHESE - RENTABILITE GLOBALE
E3: TOP MARCHES PAR MARGE
A4: Nombre de marches actifs | B4: =COUNT(Marches!H4:H25) -> 8 | E4: Marche | F4: CA/mois | G4: Marge EUR | H4: Marge %
A5: CA total / mois (EUR) | B5: =SUM(Marches!H4:H25) -> 35382 | E5: =IFERROR(INDEX(Marches!$A$4:$A$25,MATCH(LARGE(Marches!$O$4:$O$25,1),Marches!$O$4:$O$25,0)),"") -> Clinique Paris 12 (nuit) | F5: =IF($E5="","",INDEX(Marches!$H$4:$H$25,MATCH($E5,Marches!$A$4:$A$25,0))) -> 8500 | G5: =IF($E5="","",INDEX(Marches!$O$4:$O$25,MATCH($E5,Marches!$A$4:$A$25,0))) -> 1209.52 | H5: =IF($E5="","",INDEX(Marches!$P$4:$P$25,MATCH($E5,Marches!$A$4:$A$25,0))) -> 0.14229647
A6: Couts directs totaux / mois (EUR) | B6: =SUM(Marches!M4:M25) -> 34325.64 | E6: =IFERROR(INDEX(Marches!$A$4:$A$25,MATCH(LARGE(Marches!$O$4:$O$25,2),Marches!$O$4:$O$25,0)),"") -> Coworking Republique | F6: =IF($E6="","",INDEX(Marches!$H$4:$H$25,MATCH($E6,Marches!$A$4:$A$25,0))) -> 5500 | G6: =IF($E6="","",INDEX(Marches!$O$4:$O$25,MATCH($E6,Marches!$A$4:$A$25,0))) -> 743.6 | H6: =IF($E6="","",INDEX(Marches!$P$4:$P$25,MATCH($E6,Marches!$A$4:$A$25,0))) -> 0.1352
A7: Marge de contribution totale / mois (EUR) | B7: =SUM(Marches!O4:O25) -> 1056.36 | E7: =IFERROR(INDEX(Marches!$A$4:$A$25,MATCH(LARGE(Marches!$O$4:$O$25,3),Marches!$O$4:$O$25,0)),"") -> Mairie annexe Pantin | F7: =IF($E7="","",INDEX(Marches!$H$4:$H$25,MATCH($E7,Marches!$A$4:$A$25,0))) -> 2900 | G7: =IF($E7="","",INDEX(Marches!$O$4:$O$25,MATCH($E7,Marches!$A$4:$A$25,0))) -> 431.8 | H7: =IF($E7="","",INDEX(Marches!$P$4:$P$25,MATCH($E7,Marches!$A$4:$A$25,0))) -> 0.14889655
A8: Charges fixes mensuelles (EUR) | B8: =Charges_Fixes!B14 -> 3312 | E8: =IFERROR(INDEX(Marches!$A$4:$A$25,MATCH(LARGE(Marches!$O$4:$O$25,4),Marches!$O$4:$O$25,0)),"") -> Ecole primaire Montreuil | F8: =IF($E8="","",INDEX(Marches!$H$4:$H$25,MATCH($E8,Marches!$A$4:$A$25,0))) -> 1600 | G8: =IF($E8="","",INDEX(Marches!$O$4:$O$25,MATCH($E8,Marches!$A$4:$A$25,0))) -> 232.96 | H8: =IF($E8="","",INDEX(Marches!$P$4:$P$25,MATCH($E8,Marches!$A$4:$A$25,0))) -> 0.1456
A9: Resultat mensuel (EUR) | B9: =B7-B8 -> -2255.64 | E9: =IFERROR(INDEX(Marches!$A$4:$A$25,MATCH(LARGE(Marches!$O$4:$O$25,5),Marches!$O$4:$O$25,0)),"") -> Restaurant Bastille | F9: =IF($E9="","",INDEX(Marches!$H$4:$H$25,MATCH($E9,Marches!$A$4:$A$25,0))) -> 1500 | G9: =IF($E9="","",INDEX(Marches!$O$4:$O$25,MATCH($E9,Marches!$A$4:$A$25,0))) -> 224.92 | H9: =IF($E9="","",INDEX(Marches!$P$4:$P$25,MATCH($E9,Marches!$A$4:$A$25,0))) -> 0.14994667
A10: Resultat annuel (EUR) | B10: =B9*12 -> -27067.68
A11: Marge de contribution moyenne % | B11: =IF(B5=0,0,B7/B5) -> 0.029855859
A12: Marge de contribution moyenne / marche (EUR) | B12: =IF(B4=0,0,B7/B4) -> 132.045
A13: Point mort (nb marches moyens p. couvrir charges fixes) | B13: =IF(B12<=0,"n/a",B8/B12) -> 25.082358
A14: Marches rentables | B14: =COUNTIF(Marches!Q4:Q25,"OK") -> 1
A15: Marches a optimiser | B15: =COUNTIF(Marches!Q4:Q25,"A optimiser") -> 5
A16: Marches non rentables | B16: =COUNTIF(Marches!Q4:Q25,"Non rentable") -> 2
A17: Taux de marches rentables | B17: =IF(B4=0,0,B14/B4) -> 0.125
A18: Top marge mensuelle (EUR) | B18: =MAX(Marches!O4:O25) -> 1209.52

Sheet Charges_Fixes
A1: CHARGES FIXES ENTREPRISE (mensuelles)
A2: Valeurs de test a ajuster. Les agents terrain et les produits specifiques a un marche sont sur la feuille Marches.
A3: Charge fixe | B3: EUR / mois
A4: Logiciel de paie | B4: 40
A5: Service Star | B5: 50
A6: Suite Google | B6: 12
A7: Assurance professionnelle - bureau | B7: 80
A8: Assurance professionnelle - Chruth | B8: 120
A9: Hebergement | B9: 20
A10: Internet | B10: 40
A11: Eco-pepiniere (loyer) | B11: 300
A12: Produits de nettoyage (stock structure) | B12: 150
A13: Salaires (structure / encadrement) | B13: 2500
A14: Total charges fixes | B14: =SUM(B4:B13) -> 3312

Sheet Hypotheses_Marche
A1: HYPOTHESES DE CALCUL PAR MARCHE
A3: Cout horaire agent - JOUR (charge, EUR/h) | B3: 18
A4: Cout horaire agent - NUIT (charge, EUR/h) | B4: 23
A5: Semaines par mois | B5: 4.33
A6: Cout produits / mois si fournis par nous (defaut EUR) | B6: 60
A7: Taux de marge cible (repere) | B7: 0.2
A8: Coûts de l'heure/jour | B8: 20
A9: Prix minimum = cout total / (1 - marge cible) | B9: =1/(1-B7) -> 1.25
A10: Alerte marge basse si marge < cible | B10: =B7 -> 0.2

Sheet Guide_Utilisation
A1: GUIDE DU MODELE FINANCIER CHRUTH
A3: Section | B3: Utilisation
A4: Objectif | B4: Piloter la rentabilite des marches de nettoyage, relier les prix aux couts reels et prioriser la prospection.
A5: 1. Previsionnel_Global | B5: Choisir un scenario, ajuster prospects/mois, conversion, panier annuel, churn, CAPEX, impots et annee.
A6: 2. Marches | B6: Saisir les cellules jaunes : nom, jours, heures, effectif, type jour/nuit, produits, prix et amortissement.
A7: 3. Synthese_Rentabilite | B7: Lire le resultat mensuel, le point mort, le taux de marches rentables et le top marge.
A8: 4. Tableau_de_Bord | B8: Utiliser les KPI et graphiques pour presenter la decision business.
A9: Lien fiche de poste | B9: Le modele couvre la mission CRM/rentabilite et complete la segmentation/scoring des prospects.
A10: Version nettoyee | B10: Le dossier garde les livrables et scripts utiles ; les logs, tests, caches et donnees brutes massives sont regenerables.
